yafcorse/__init__.py
yafcorse-1.0.0.dist-info/LICENSE
yafcorse-1.0.0.dist-info/METADATA
yafcorse-1.0.0.dist-info/WHEEL
yafcorse-1.0.0.dist-info/top_level.txt
yafcorse-1.0.0.dist-info/RECORD
