Metadata-Version: 2.1
Name: yafcorse
Version: 1.0.0
Summary: Yet Another Flask CORS Extension.
Home-page: https://github.com/pyfaddist/yafcorse
Author: Christian Dein
Author-email: christian.dein@dein-hosting.de
License: MIT
Platform: UNKNOWN
Classifier: Programming Language :: Python :: 3
Classifier: License :: OSI Approved :: MIT License
Classifier: Operating System :: OS Independent
Requires-Python: >=3.6
License-File: LICENSE
